inferx/__init__.py
inferx/base.py
inferx/config.py
inferx/runtime.py
inferx/backend/__init__.py
inferx/backend/onx/__init__.py
inferx/backend/onx/onnx_backend.py
inferx/backend/trt/__init__.py
inferx/backend/trt/tensorrt_backend.py
inferx/backend/trt/utils.py
inferx/backend/trt/convert/__init__.py
inferx/backend/trt/convert/dynamic_axis.py
inferx/backend/trt/convert/onnx_tensorrt.py
inferx-1.1.2.dist-info/METADATA
inferx-1.1.2.dist-info/WHEEL
inferx-1.1.2.dist-info/top_level.txt
inferx-1.1.2.dist-info/RECORD
